code/fp_adder.vhd
library ieee;
use ieee.std_logic_1164.all;
use ieee.numeric_std.all;

entity fp_adder is
    port (
        sign1, sign2: in std_logic;
        exp1, exp2: in std_logic_vector(3 downto 0);
        frac1, frac2: in std_logic_vector(7 downto 0);
        sign_out: out std_logic;
        exp_out: out std_logic_vector(3 downto 0);
        frac_out: out std_logic_vector(7 downto 0)
    );
end fp_adder;

architecture arch of fp_adder is
    -- suffix b, s, a, n for big, small, aligned, normalized number
    signal signb, signs: std_logic;
    signal expb, exps, expn: unsigned(3 downto 0);
    signal fracb, fracs, fraca, fracn: unsigned(7 downto 0);
    signal sum_norm: unsigned(7 downto 0);
    signal exp_diff: unsigned(3 downto 0);
    signal sum: unsigned(8 downto 0); -- one extra for carry
    signal lead0: unsigned(2 downto 0);
begin
    -- 1st stage: sort to find the larger number
    process (sign1, sign2, exp1, exp2, frac1, frac2)
    begin
        if (exp1 & frac1) > (exp2 & frac2) then
            signb <= sign1;
            signs <= sign2;
            expb <= unsigned(exp1);
            exps <= unsigned(exp2);
            fracb <= unsigned(frac1);
            fracs <= unsigned(frac2);
        else
            signb <= sign2;
            signs <= sign1;
            expb <= unsigned(exp2);
            exps <= unsigned(exp1);
            fracb <= unsigned(frac2);
            fracs <= unsigned(frac1);
        end if;
    end process;

    -- 2nd stage: align smaller number
    exp_diff <= expb - exps;
    with exp_diff select
        fraca <=
            fracs                         when "0000",
            "0"       & fracs(7 downto 1) when "0001",
            "00"      & fracs(7 downto 2) when "0010",
            "000"     & fracs(7 downto 3) when "0011",
            "0000"    & fracs(7 downto 4) when "0100",
            "00000"   & fracs(7 downto 5) when "0101",
            "000000"  & fracs(7 downto 6) when "0110",
            "0000000" & fracs(7)          when "0111",
            "00000000"                    when others;

    -- 3rd stage: add/subtract
    sum <= ('0' & fracb) + ('0' & fraca) when signb = signs else
           ('0' & fracb) - ('0' & fraca);

    -- 4th stage: normalize
    -- count leading Os
    lead0 <= "000" when (sum(7)='1') else
             "001" when (sum(6)='1') else
             "010" when (sum(5)='1') else
             "011" when (sum(4)='1') else
             "100" when (sum(3)='1') else
             "101" when (sum(2)='1') else
             "110" when (sum(1)='1') else
             "111";

    -- shift significand according to leading O
    with lead0 select
        sum_norm <=
            sum(7 downto 0)             when "000",
            sum(6 downto 0) & '0'       when "001",
            sum(5 downto 0) & "00"      when "010",
            sum(4 downto 0) & "000"     when "011",
            sum(3 downto 0) & "0000"    when "100",
            sum(2 downto 0) & "00000"   when "101",
            sum(1 downto 0) & "000000"  when "110",
            sum(0) &          "0000000" when others;

    -- normalize with special conditions
    process (sum, sum_norm, expb, lead0)
    begin
        if sum(8) = '1' then -- w/ carry out; shift frac to right
            expn <= expb + 1;
            fracn <= sum(8 downto 1);
        elsif (lead0 > expb) then    -- too small to normalize;
            expn <= (others => '0'); -- set to 0
            fracn <= (others => '0');
        else
            expn <= expb - lead0;
            fracn <= sum_norm;
        end if;
    end process;

    -- form output
    sign_out <= signb;
    exp_out <= std_logic_vector(expn);
    frac_out <= std_logic_vector(fracn);
end arch;

code/fp_adder_testbench.vhd
library ieee;
use ieee.std_logic_1164.all;

entity fp_adder_tb is
end fp_adder_tb;

architecture tb_arch of fp_adder_tb is
    -- input signals
    signal t_sign1, t_sign2: std_logic;
    signal t_exp1, t_exp2: std_logic_vector(3 downto 0);
    signal t_frac1, t_frac2: std_logic_vector(7 downto 0);

    -- output signals
    signal t_sign_out: std_logic;
    signal t_exp_out: std_logic_vector(3 downto 0);
    signal t_frac_out: std_logic_vector(7 downto 0);
begin
    -- instantiate the unit under test (uut)
    uut: entity work.fp_adder(arch)
        port map(
            sign1 => t_sign1, sign2 => t_sign2,
            exp1 => t_exp1, exp2 => t_exp2,
            frac1 => t_frac1, frac2 => t_frac2,
            sign_out => t_sign_out,
            exp_out => t_exp_out,
            frac_out => t_frac_out
        );

    -- generate test vectors
    process
    begin
        -- test vector 1: sum with no special cases in normalization
        t_sign1 <= '0';
        t_exp1  <= "0111";
        t_frac1 <= "10000000";
        t_sign2 <= '0';
        t_exp2  <= "0101";
        t_frac2 <= "11000000";
        wait for 200 ns;

        -- test vector 2: sum with carry out
        t_sign1 <= '0';
        t_exp1  <= "0100";
        t_frac1 <= "10000000";
        t_sign2 <= '0';
        t_exp2  <= "0100";
        t_frac2 <= "10000000";
        wait for 200 ns;

        -- test vector 3: subtraction with left shift
        t_sign1 <= '0';
        t_exp1  <= "0101";
        t_frac1 <= "10001000";
        t_sign2 <= '1';
        t_exp2  <= "0101";
        t_frac2 <= "10000000";
        wait for 200 ns;
        
        -- test vector 4: subtraction w/ too small result
        t_sign1 <= '0';
        t_exp1  <= "0100";
        t_frac1 <= "11110100";
        t_sign2 <= '1';
        t_exp2  <= "0100";
        t_frac2 <= "11110000";
        wait for 200 ns;
        
        -- test vector 5: subtraction w/ too small result
        t_sign1 <= '0';
        t_exp1  <= "0000";
        t_frac1 <= "11111111";
        t_sign2 <= '1';
        t_exp2  <= "0000";
        t_frac2 <= "10000000";
        wait for 200 ns;
        
        -- test vector 6: addition w/ too big result
        t_sign1 <= '0';
        t_exp1  <= "1111";
        t_frac1 <= "11111111";
        t_sign2 <= '0';
        t_exp2  <= "1000";
        t_frac2 <= "10000000";
        wait for 200 ns;
        
        -- test vector 7: big + small, losing bits
        t_sign1 <= '0';
        t_exp1  <= "1011";
        t_frac1 <= "10000000";
        t_sign2 <= '0';
        t_exp2  <= "0011";
        t_frac2 <= "11111111";
        wait for 200 ns;
        
        -- test vector 8: subtraction of equals w/ nonzero exponent
        t_sign1 <= '0';
        t_exp1  <= "1111";
        t_frac1 <= "11110000";
        t_sign2 <= '1';
        t_exp2  <= "1111";
        t_frac2 <= "11110000";
        wait for 200 ns;
        
        wait;
    end process;
end tb_arch;

code/wave.vcd
$date
  Sun Aug  9 16:33:02 2026
$end
$version
  GHDL v0
$end
$timescale
  1 fs
$end
$scope module standard $end
$upscope $end
$scope module std_logic_1164 $end
$upscope $end
$scope module numeric_std $end
$upscope $end
$scope module fp_adder_tb $end
$var reg 1 ! t_sign1 $end
$var reg 1 " t_sign2 $end
$var reg 4 # t_exp1[3:0] $end
$var reg 4 $ t_exp2[3:0] $end
$var reg 8 % t_frac1[7:0] $end
$var reg 8 & t_frac2[7:0] $end
$var reg 1 ' t_sign_out $end
$var reg 4 ( t_exp_out[3:0] $end
$var reg 8 ) t_frac_out[7:0] $end
$scope module uut $end
$var reg 1 * sign1 $end
$var reg 1 + sign2 $end
$var reg 4 , exp1[3:0] $end
$var reg 4 - exp2[3:0] $end
$var reg 8 . frac1[7:0] $end
$var reg 8 / frac2[7:0] $end
$var reg 1 0 sign_out $end
$var reg 4 1 exp_out[3:0] $end
$var reg 8 2 frac_out[7:0] $end
$var reg 1 3 signb $end
$var reg 1 4 signs $end
$var reg 4 5 expb[3:0] $end
$var reg 4 6 exps[3:0] $end
$var reg 4 7 expn[3:0] $end
$var reg 8 8 fracb[7:0] $end
$var reg 8 9 fracs[7:0] $end
$var reg 8 : fraca[7:0] $end
$var reg 8 ; fracn[7:0] $end
$var reg 8 < sum_norm[7:0] $end
$var reg 4 = exp_diff[3:0] $end
$var reg 9 > sum[8:0] $end
$var reg 3 ? lead0[2:0] $end
$upscope $end
$upscope $end
$enddefinitions $end
#0
0!
0"
b0100 #
b0100 $
b10000000 %
b10000000 &
0'
b0101 (
b10000000 )
0*
0+
b0100 ,
b0100 -
b10000000 .
b10000000 /
00
b0101 1
b10000000 2
03
04
b0100 5
b0100 6
b0101 7
b10000000 8
b10000000 9
b10000000 :
b10000000 ;
b00000000 <
b0000 =
b100000000 >
b111 ?
#200000000
1"
b0101 #
b0101 $
b10000100 %
b0000 (
b10000000 )
1+
b0101 ,
b0101 -
b10000100 .
b0000 1
b10000000 2
14
b0101 5
b0101 6
b0000 7
b10000100 8
b10000000 ;
b10000000 <
b000000100 >
b101 ?
#400000000
0"
b0111 #
b10000000 %
b11000000 &
b0111 (
b10110000 )
0+
b0111 ,
b10000000 .
b11000000 /
b0111 1
b10110000 2
04
b0111 5
b0111 7
b10000000 8
b11000000 9
b00110000 :
b10110000 ;
b10110000 <
b0010 =
b010110000 >
b000 ?
#600000000
1"
b0100 #
b1000 $
b10100000 %
b11000111 &
1'
b1000 (
b10111101 )
1+
b0100 ,
b1000 -
b10100000 .
b11000111 /
10
b1000 1
b10111101 2
13
b1000 5
b0100 6
b1000 7
b11000111 8
b10100000 9
b00001010 :
b10111101 ;
b10111101 <
b0100 =
b010111101 >
#800000000
b0000 #
b0000 $
b11111111 %
b10000000 &
0'
b0000 (
b00000000 )
b0000 ,
b0000 -
b11111111 .
b10000000 /
00
b0000 1
b00000000 2
03
14
b0000 5
b0000 6
b0000 7
b11111111 8
b10000000 9
b10000000 :
b00000000 ;
b11111110 <
b0000 =
b001111111 >
b001 ?
#1000000000
0"
b1111 #
b1000 $
b0000 (
b10000000 )
0+
b1111 ,
b1000 -
b0000 1
b10000000 2
04
b1111 5
b1000 6
b0000 7
b00000001 :
b10000000 ;
b00000000 <
b0111 =
b100000000 >
b111 ?
#1200000000
b1011 #
b0011 $
b10000000 %
b11111111 &
b1011 (
b10000000 )
b1011 ,
b0011 -
b10000000 .
b11111111 /
b1011 1
b10000000 2
b1011 5
b0011 6
b1011 7
b10000000 8
b11111111 9
b00000000 :
b10000000 ;
b10000000 <
b1000 =
b010000000 >
b000 ?
#1400000000
1"
b1111 #
b1111 $
b11110000 %
b11110000 &
1'
b1000 (
b00000000 )
1+
b1111 ,
b1111 -
b11110000 .
b11110000 /
10
b1000 1
b00000000 2
13
b1111 5
b1111 6
b1000 7
b11110000 8
b11110000 9
b11110000 :
b00000000 ;
b00000000 <
b0000 =
b000000000 >
b111 ?
